drf_psq/__init__.py
drf_psq/apps.py
drf_psq/decorator.py
drf_psq/mixins.py
drf_psq/utils.py
drf_psq-1.1.0.dist-info/LICENSE
drf_psq-1.1.0.dist-info/METADATA
drf_psq-1.1.0.dist-info/WHEEL
drf_psq-1.1.0.dist-info/top_level.txt
drf_psq-1.1.0.dist-info/RECORD
