Metadata-Version: 2.1
Name: drf-psq
Version: 1.1.0
Summary: The simplest and most general way to manage action-based permissions, serializers, and querysets dependent on permission-based rules for the Django REST framework!
Home-page: UNKNOWN
Author: AminHP
Author-email: mdan.hagh@gmail.com
License: MIT
Platform: UNKNOWN
Requires-Dist: django
Requires-Dist: djangorestframework
